{
  "schema_version": "v1",
  "name_for_human": "Uberchord",
  "name_for_model": "uberchord",
  "description_for_human": "通过指定和弦名称查找吉他和弦图。",
  "description_for_model": "获取吉他和弦图及其在吉他品格上的位置。",
  "auth": {
    "type": "none"
  },
  "api": {
    "type": "openapi",
    "url": "https://guitarchords.pluginboost.com/.well-known/openapi.yaml",
    "is_user_authenticated": false
  },
  "logo_url": "/assets/uberchord.png",
  "contact_email": "info.bluelightweb@gmail.com",
  "legal_info_url": "https://guitarchords.pluginboost.com/legal"
}
